{"frames": {

"emoticon_14_00.png":
{
	"frame": {"x":1169,"y":255,"w":262,"h":280},
	"rotated": true,
	"trimmed": true,
	"spriteSourceSize": {"x":0,"y":40,"w":262,"h":280},
	"sourceSize": {"w":320,"h":320}
},
"emoticon_14_01.png":
{
	"frame": {"x":1451,"y":256,"w":262,"h":280},
	"rotated": true,
	"trimmed": true,
	"spriteSourceSize": {"x":0,"y":40,"w":262,"h":280},
	"sourceSize": {"w":320,"h":320}
},
"emoticon_14_02.png":
{
	"frame": {"x":577,"y":252,"w":259,"h":280},
	"rotated": true,
	"trimmed": true,
	"spriteSourceSize": {"x":0,"y":40,"w":259,"h":280},
	"sourceSize": {"w":320,"h":320}
},
"emoticon_14_03.png":
{
	"frame": {"x":1054,"y":1,"w":249,"h":276},
	"rotated": true,
	"trimmed": true,
	"spriteSourceSize": {"x":0,"y":44,"w":249,"h":276},
	"sourceSize": {"w":320,"h":320}
},
"emoticon_14_04.png":
{
	"frame": {"x":256,"y":1,"w":237,"h":258},
	"rotated": true,
	"trimmed": true,
	"spriteSourceSize": {"x":0,"y":62,"w":237,"h":258},
	"sourceSize": {"w":320,"h":320}
},
"emoticon_14_05.png":
{
	"frame": {"x":516,"y":1,"w":237,"h":258},
	"rotated": true,
	"trimmed": true,
	"spriteSourceSize": {"x":0,"y":62,"w":237,"h":258},
	"sourceSize": {"w":320,"h":320}
},
"emoticon_14_06.png":
{
	"frame": {"x":283,"y":501,"w":262,"h":280},
	"rotated": true,
	"trimmed": true,
	"spriteSourceSize": {"x":0,"y":40,"w":262,"h":280},
	"sourceSize": {"w":320,"h":320}
},
"emoticon_14_07.png":
{
	"frame": {"x":616,"y":791,"w":292,"h":280},
	"rotated": false,
	"trimmed": true,
	"spriteSourceSize": {"x":0,"y":40,"w":292,"h":280},
	"sourceSize": {"w":320,"h":320}
},
"emoticon_14_08.png":
{
	"frame": {"x":910,"y":801,"w":291,"h":308},
	"rotated": true,
	"trimmed": true,
	"spriteSourceSize": {"x":0,"y":12,"w":291,"h":308},
	"sourceSize": {"w":320,"h":320}
},
"emoticon_14_09.png":
{
	"frame": {"x":1220,"y":802,"w":291,"h":308},
	"rotated": true,
	"trimmed": true,
	"spriteSourceSize": {"x":0,"y":12,"w":291,"h":308},
	"sourceSize": {"w":320,"h":320}
},
"emoticon_14_10.png":
{
	"frame": {"x":1332,"y":1,"w":252,"h":253},
	"rotated": true,
	"trimmed": true,
	"spriteSourceSize": {"x":0,"y":67,"w":252,"h":253},
	"sourceSize": {"w":320,"h":320}
},
"emoticon_14_11.png":
{
	"frame": {"x":1151,"y":519,"w":291,"h":280},
	"rotated": false,
	"trimmed": true,
	"spriteSourceSize": {"x":0,"y":40,"w":291,"h":280},
	"sourceSize": {"w":320,"h":320}
},
"emoticon_14_12.png":
{
	"frame": {"x":1444,"y":520,"w":320,"h":280},
	"rotated": false,
	"trimmed": true,
	"spriteSourceSize": {"x":0,"y":40,"w":320,"h":280},
	"sourceSize": {"w":320,"h":320}
},
"emoticon_14_13.png":
{
	"frame": {"x":1,"y":765,"w":320,"h":280},
	"rotated": false,
	"trimmed": true,
	"spriteSourceSize": {"x":0,"y":40,"w":320,"h":280},
	"sourceSize": {"w":320,"h":320}
},
"emoticon_14_14.png":
{
	"frame": {"x":1530,"y":802,"w":320,"h":298},
	"rotated": false,
	"trimmed": true,
	"spriteSourceSize": {"x":0,"y":22,"w":320,"h":298},
	"sourceSize": {"w":320,"h":320}
},
"emoticon_14_15.png":
{
	"frame": {"x":1,"y":1,"w":237,"h":253},
	"rotated": true,
	"trimmed": true,
	"spriteSourceSize": {"x":0,"y":67,"w":237,"h":253},
	"sourceSize": {"w":320,"h":320}
},
"emoticon_14_16.png":
{
	"frame": {"x":1733,"y":256,"w":262,"h":280},
	"rotated": true,
	"trimmed": true,
	"spriteSourceSize": {"x":0,"y":40,"w":262,"h":280},
	"sourceSize": {"w":320,"h":320}
},
"emoticon_14_17.png":
{
	"frame": {"x":1,"y":495,"w":262,"h":280},
	"rotated": true,
	"trimmed": true,
	"spriteSourceSize": {"x":0,"y":40,"w":262,"h":280},
	"sourceSize": {"w":320,"h":320}
},
"emoticon_14_18.png":
{
	"frame": {"x":295,"y":240,"w":259,"h":280},
	"rotated": true,
	"trimmed": true,
	"spriteSourceSize": {"x":0,"y":40,"w":259,"h":280},
	"sourceSize": {"w":320,"h":320}
},
"emoticon_14_19.png":
{
	"frame": {"x":776,"y":1,"w":249,"h":276},
	"rotated": true,
	"trimmed": true,
	"spriteSourceSize": {"x":0,"y":44,"w":249,"h":276},
	"sourceSize": {"w":320,"h":320}
},
"emoticon_14_20.png":
{
	"frame": {"x":1587,"y":1,"w":292,"h":253},
	"rotated": false,
	"trimmed": true,
	"spriteSourceSize": {"x":0,"y":67,"w":292,"h":253},
	"sourceSize": {"w":320,"h":320}
},
"emoticon_14_21.png":
{
	"frame": {"x":1,"y":240,"w":292,"h":253},
	"rotated": false,
	"trimmed": true,
	"spriteSourceSize": {"x":0,"y":67,"w":292,"h":253},
	"sourceSize": {"w":320,"h":320}
},
"emoticon_14_22.png":
{
	"frame": {"x":323,"y":791,"w":291,"h":280},
	"rotated": false,
	"trimmed": true,
	"spriteSourceSize": {"x":0,"y":40,"w":291,"h":280},
	"sourceSize": {"w":320,"h":320}
},
"emoticon_14_23.png":
{
	"frame": {"x":859,"y":252,"w":259,"h":308},
	"rotated": true,
	"trimmed": true,
	"spriteSourceSize": {"x":0,"y":12,"w":259,"h":308},
	"sourceSize": {"w":320,"h":320}
},
"emoticon_14_24.png":
{
	"frame": {"x":565,"y":513,"w":291,"h":276},
	"rotated": false,
	"trimmed": true,
	"spriteSourceSize": {"x":0,"y":44,"w":291,"h":276},
	"sourceSize": {"w":320,"h":320}
},
"emoticon_14_25.png":
{
	"frame": {"x":858,"y":513,"w":291,"h":276},
	"rotated": false,
	"trimmed": true,
	"spriteSourceSize": {"x":0,"y":44,"w":291,"h":276},
	"sourceSize": {"w":320,"h":320}
}},
"animations": {
	"emoticon_14": ["emoticon_14_00.png","emoticon_14_01.png","emoticon_14_02.png","emoticon_14_03.png","emoticon_14_04.png","emoticon_14_05.png","emoticon_14_06.png","emoticon_14_07.png","emoticon_14_08.png","emoticon_14_09.png","emoticon_14_10.png","emoticon_14_11.png","emoticon_14_12.png","emoticon_14_13.png","emoticon_14_14.png","emoticon_14_15.png","emoticon_14_16.png","emoticon_14_17.png","emoticon_14_18.png","emoticon_14_19.png","emoticon_14_20.png","emoticon_14_21.png","emoticon_14_22.png","emoticon_14_23.png","emoticon_14_24.png","emoticon_14_25.png"]
},
"meta": {
	"app": "https://www.codeandweb.com/texturepacker",
	"version": "1.0",
	"image": "emoticon_14.png",
	"format": "RGBA8888",
	"size": {"w":2014,"h":1101},
	"scale": "1",
	"smartupdate": "$TexturePacker:SmartUpdate:1e46912d22db8d1db2a9cb3f5b99fe86:860cfec293a4dee174b8d17b09e7a0d1:fb004635bd93c098578f69870573bd71$"
}
}
